peargent/__init__.py
peargent/cli.py
peargent/_config/__init__.py
peargent/_config/history.py
peargent/_core/__init__.py
peargent/_core/agent.py
peargent/_core/pool.py
peargent/_core/router.py
peargent/_core/state.py
peargent/_core/stopping.py
peargent/_core/streaming.py
peargent/_core/tool.py
peargent/_templates/follow_up_prompt.j2
peargent/_templates/no_tools_prompt.j2
peargent/_templates/routing_prompt.j2
peargent/_templates/structured_output_prompt.j2
peargent/_templates/summarization_prompt.j2
peargent/_templates/tools_prompt.j2
peargent/atlas/__init__.py
peargent/atlas/loader.py
peargent/atlas/serializer.py
peargent/history/__init__.py
peargent/history/history.py
peargent/models/__init__.py
peargent/models/anthropic.py
peargent/models/azure_openai.py
peargent/models/base.py
peargent/models/gemini.py
peargent/models/groq.py
peargent/models/openai.py
peargent/observability/__init__.py
peargent/observability/async_database_store.py
peargent/observability/context.py
peargent/observability/cost_tracker.py
peargent/observability/database_store.py
peargent/observability/formatters.py
peargent/observability/redis_store.py
peargent/observability/span.py
peargent/observability/store.py
peargent/observability/trace.py
peargent/observability/tracer.py
peargent/storage/__init__.py
peargent/storage/base.py
peargent/storage/file.py
peargent/storage/postgresql.py
peargent/storage/redis.py
peargent/storage/session_buffer.py
peargent/storage/sqlite.py
peargent/storage/storage_types.py
peargent/tools/__init__.py
peargent/tools/datetime_tool.py
peargent/tools/discord_tool.py
peargent/tools/email_tool.py
peargent/tools/math_tool.py
peargent/tools/text_extraction_tool.py
peargent/tools/websearch_tool.py
peargent/tools/wikipedia_tool.py
peargent-0.1.5.dist-info/licenses/LICENSE
peargent-0.1.5.dist-info/METADATA
peargent-0.1.5.dist-info/WHEEL
peargent-0.1.5.dist-info/entry_points.txt
peargent-0.1.5.dist-info/top_level.txt
peargent-0.1.5.dist-info/RECORD
