Metadata-Version: 2.4
Name: peargent
Version: 0.1.5
Summary: A modern Python framework for building intelligent AI agents with advanced tracing, history management, and seamless LLM integration
Author-email: Quanta-Naut <quantanaut@peargent.online>
License: 
Project-URL: Homepage, https://github.com/Peargent/peargent
Project-URL: Documentation, https://your-docs-url-here
Project-URL: Bug Tracker, https://github.com/Peargent/peargent/issues
Project-URL: Source Code, https://github.com/Peargent/peargent
Keywords: ai,agents,llm,openai,anthropic,groq,tracing,observability,chatbot,agentic,automation
Classifier: Development Status :: 4 - Beta
Classifier: Intended Audience :: Developers
Classifier: License :: OSI Approved :: MIT License
Classifier: Programming Language :: Python :: 3
Classifier: Programming Language :: Python :: 3.9
Classifier: Programming Language :: Python :: 3.10
Classifier: Programming Language :: Python :: 3.11
Classifier: Programming Language :: Python :: 3.12
Classifier: Topic :: Software Development :: Libraries :: Python Modules
Classifier: Topic :: Scientific/Engineering :: Artificial Intelligence
Requires-Python: >=3.9
License-File: LICENSE
Requires-Dist: requests>=2.31
Requires-Dist: python-dotenv>=1.0
Requires-Dist: pydantic>=2.0
Requires-Dist: tiktoken>=0.5.0
Requires-Dist: sqlalchemy>=2.0.0
Requires-Dist: jinja2>=3.0.0
Provides-Extra: dev
Requires-Dist: pytest; extra == "dev"
Requires-Dist: black; extra == "dev"
Requires-Dist: flake8; extra == "dev"
Provides-Extra: postgresql
Requires-Dist: psycopg2-binary>=2.9.0; extra == "postgresql"
Provides-Extra: text-extraction
Requires-Dist: beautifulsoup4>=4.12.3; extra == "text-extraction"
Requires-Dist: pypdf>=6.0.0; extra == "text-extraction"
Requires-Dist: python-docx>=1.1.0; extra == "text-extraction"
Provides-Extra: web-search
Requires-Dist: ddgs>=9.0.0; extra == "web-search"
Dynamic: license-file
